Workbook

Sheet Compensation_Band_Model
A1: Job Role | B1: Headcount | C1: Avg Monthly Income | D1: Band Midpoint | E1: Compa-Ratio | F1: Avg Overtime Hours
A2: HR Manager | B2: 42 | C2: 8919 | D2: 9000 | E2: =C2/D2 -> 0.991 | F2: 20
A3: HR Specialist | B3: 38 | C3: 5309 | D3: 5200 | E3: =C3/D3 -> 1.0209615 | F3: 21.1
A4: Laboratory Technician | B4: 111 | C4: 4684 | D4: 4800 | E4: =C4/D4 -> 0.97583333 | F4: 18.2
A5: Marketing Analyst | B5: 68 | C5: 5414 | D5: 5500 | E5: =C5/D5 -> 0.98436364 | F5: 18.8
A6: Marketing Manager | B6: 70 | C6: 9534 | D6: 9500 | E6: =C6/D6 -> 1.0035789 | F6: 16.7
A7: Research Scientist | B7: 136 | C7: 6834 | D7: 7000 | E7: =C7/D7 -> 0.97628571 | F7: 20
A8: Sales Executive | B8: 142 | C8: 6439 | D8: 6500 | E8: =C8/D8 -> 0.99061538 | F8: 19.1
A9: Sales Representative | B9: 143 | C9: 4596 | D9: 4500 | E9: =C9/D9 -> 1.0213333 | F9: 20.6
A10: Senior Engineer | B10: 126 | C10: 11314 | D10: 11500 | E10: =C10/D10 -> 0.98382609 | F10: 18.1
A11: Software Engineer | B11: 124 | C11: 8560 | D11: 8500 | E11: =C11/D11 -> 1.0070588 | F11: 18.4

Sheet Attrition_Cost_Calculator
A1: Job Role | B1: Leavers | C1: Avg Annual Salary | D1: Recruitment (0.3x) | E1: Training (0.2x) | F1: Lost Productivity (1.0x) | G1: Cost per Leaver | H1: Total Attrition Cost
A2: HR Manager | B2: 9 | C2: ='Compensation_Band_Model'!C2*12 -> 107028 | D2: =C2*0.3 -> 32108.4 | E2: =C2*0.2 -> 21405.6 | F2: =C2*1.0 -> 107028 | G2: =SUM(D2:F2) -> 160542 | H2: =B2*G2 -> 1444878
A3: HR Specialist | B3: 6 | C3: ='Compensation_Band_Model'!C3*12 -> 63708 | D3: =C3*0.3 -> 19112.4 | E3: =C3*0.2 -> 12741.6 | F3: =C3*1.0 -> 63708 | G3: =SUM(D3:F3) -> 95562 | H3: =B3*G3 -> 573372
A4: Laboratory Technician | B4: 16 | C4: ='Compensation_Band_Model'!C4*12 -> 56208 | D4: =C4*0.3 -> 16862.4 | E4: =C4*0.2 -> 11241.6 | F4: =C4*1.0 -> 56208 | G4: =SUM(D4:F4) -> 84312 | H4: =B4*G4 -> 1348992
A5: Marketing Analyst | B5: 17 | C5: ='Compensation_Band_Model'!C5*12 -> 64968 | D5: =C5*0.3 -> 19490.4 | E5: =C5*0.2 -> 12993.6 | F5: =C5*1.0 -> 64968 | G5: =SUM(D5:F5) -> 97452 | H5: =B5*G5 -> 1656684
A6: Marketing Manager | B6: 15 | C6: ='Compensation_Band_Model'!C6*12 -> 114408 | D6: =C6*0.3 -> 34322.4 | E6: =C6*0.2 -> 22881.6 | F6: =C6*1.0 -> 114408 | G6: =SUM(D6:F6) -> 171612 | H6: =B6*G6 -> 2574180
A7: Research Scientist | B7: 19 | C7: ='Compensation_Band_Model'!C7*12 -> 82008 | D7: =C7*0.3 -> 24602.4 | E7: =C7*0.2 -> 16401.6 | F7: =C7*1.0 -> 82008 | G7: =SUM(D7:F7) -> 123012 | H7: =B7*G7 -> 2337228
A8: Sales Executive | B8: 24 | C8: ='Compensation_Band_Model'!C8*12 -> 77268 | D8: =C8*0.3 -> 23180.4 | E8: =C8*0.2 -> 15453.6 | F8: =C8*1.0 -> 77268 | G8: =SUM(D8:F8) -> 115902 | H8: =B8*G8 -> 2781648
A9: Sales Representative | B9: 22 | C9: ='Compensation_Band_Model'!C9*12 -> 55152 | D9: =C9*0.3 -> 16545.6 | E9: =C9*0.2 -> 11030.4 | F9: =C9*1.0 -> 55152 | G9: =SUM(D9:F9) -> 82728 | H9: =B9*G9 -> 1820016
A10: Senior Engineer | B10: 27 | C10: ='Compensation_Band_Model'!C10*12 -> 135768 | D10: =C10*0.3 -> 40730.4 | E10: =C10*0.2 -> 27153.6 | F10: =C10*1.0 -> 135768 | G10: =SUM(D10:F10) -> 203652 | H10: =B10*G10 -> 5498604
A11: Software Engineer | B11: 16 | C11: ='Compensation_Band_Model'!C11*12 -> 102720 | D11: =C11*0.3 -> 30816 | E11: =C11*0.2 -> 20544 | F11: =C11*1.0 -> 102720 | G11: =SUM(D11:F11) -> 154080 | H11: =B11*G11 -> 2465280
A12: TOTAL | B12: =SUM(B2:B11) -> 171 | H12: =SUM(H2:H11) -> 22500882
